{
    "numberOfPages": 140,
    "img_001": {
        "page": "1",
        "pageWidth": "600",
        "pageHeight": "848",
        "sections": {
            "1": {
                "class": "text",
                "x": 253,
                "y": 543,
                "height": 24,
                "width": 94,
                "leftCorner": [
                    253,
                    543
                ],
                "rightCorner": [
                    347,
                    567
                ],
                "text": "4 TUNIE 2010"
            },
            "2": {
                "class": "text",
                "x": 254,
                "y": 404,
                "height": 23,
                "width": 92,
                "leftCorner": [
                    254,
                    404
                ],
                "rightCorner": [
                    346,
                    427
                ],
                "text": "EDITIA A III-A"
            },
            "3": {
                "class": "text",
                "x": 159,
                "y": 348,
                "height": 40,
                "width": 284,
                "leftCorner": [
                    159,
                    348
                ],
                "rightCorner": [
                    443,
                    388
                ],
                "text": "IN SCOALA ROMANEASCA"
            },
            "4": {
                "class": "text",
                "x": 118,
                "y": 312,
                "height": 36,
                "width": 364,
                "leftCorner": [
                    118,
                    312
                ],
                "rightCorner": [
                    482,
                    348
                ],
                "text": "CREATIVITATE $I MODERNITATE"
            },
            "5": {
                "class": "text",
                "x": 68,
                "y": 248,
                "height": 31,
                "width": 463,
                "leftCorner": [
                    68,
                    248
                ],
                "rightCorner": [
                    531,
                    279
                ],
                "text": "SIMPOZIONUL NATIONAL DE COMUNICARI STIINTIFICE"
            },
            "6": {
                "class": "text",
                "x": 152,
                "y": 53,
                "height": 27,
                "width": 294,
                "leftCorner": [
                    152,
                    53
                ],
                "rightCorner": [
                    446,
                    80
                ],
                "text": "GRUP $COLAR ,,ANGHEL SALIGNY\u201d IASI"
            }
        }
    },
    "img_002": {
        "page": "2",
        "pageWidth": "600",
        "pageHeight": "848",
        "sections": {
            "7": {
                "class": "text",
                "x": 133,
                "y": 718,
                "height": 40,
                "width": 333,
                "leftCorner": [
                    133,
                    718
                ],
                "rightCorner": [
                    466,
                    758
                ],
                "text": "Responsabilitatea pentru cor\nautoriloi\n\njutul materialelor apartine"
            },
            "8": {
                "class": "text",
                "x": 235,
                "y": 573,
                "height": 25,
                "width": 119,
                "leftCorner": [
                    235,
                    573
                ],
                "rightCorner": [
                    354,
                    598
                ],
                "text": "ISSN: 2068-5564"
            }
        }
    },
    "img_003": {
        "page": "3",
        "pageWidth": "600",
        "pageHeight": "848",
        "sections": {
            "9": {
                "class": "text",
                "x": 50,
                "y": 124,
                "height": 666,
                "width": 499,
                "leftCorner": [
                    50,
                    124
                ],
                "rightCorner": [
                    549,
                    790
                ],
                "text": "1. INVATAREA PRINS\nProfesor Manuela HUTUPASU\nLiceul Teoretic ,Miron Cost\n\n \n\nbasi\nProfesor Mihaela SIMONCA\n\n\u2018Colegiul National 1. L. Caragiale\u201d Bucuresti\n\n2. INFLUENTA ASEZARILOR DIN JUDETUL IASI ASUPRA MEDIULUL\n\n \n\nProfesor Ma\n\n \n   \n\n3. JOCU LOC DE EXERSARE A CAPACITATI DE\nINTERACTIUNE INTERPERSONAL A ossnsnsnnennnnnsnannnnnenenannnenned\nProfesor Mihaela VARODI\n\nGrup Scolar ,Anghel Saligny\u201d lai\n\n4.\u201d CRITICA TEMATICA.\nProfesor Alina-Eugenia ZLEL\nScoala Nr. 2 .Dimitrie Cantemit\u201d Vaslui\n5, POLITICA RELIGIOASA A REGIMULUI CARLIST (1938 \u2014 1940).\nProfesor Costel COAJA\n\nGrup Seolar ,Anghel Saligny\u201d lagi\n\n6. INTELEGEREA ALTERITATH $1 AUTOCUNOASTEREA PRIN\nINTERCULTURALITATE\n\nProfesor Nicu CRACIUN\n\nLiceul Teoretic Vasile Alecsandri\u201d Iasi\n7. CREATIVITATEA ~ ELEMENT CHEIE IN INVATAMANTUL TEHNIC.\nProfesor Rodica DUMITRU\n\nColegiul Tehnic .Gh. Asachi\u201d lagi\n\n8, EDUCATIA SI MANAGEMENTUL STRESULUI PROFESIONAL.\nProfesor Catlin Constantin 1OA\\\n\nProfesor psihopedagog Cristina VAMESU,\nGrup Seolar ,Anghel Saligny\u201d lasi\n\n9.\u201c ROLUL EDUCATIEI PERMANENT!\nProfesor Natalia Alina COPACEL\n\nGrup Scolar .Anghel Saligny\u201d lagi\n\n10.\u201d PROIECTELE INTERNATIONALE COMENIUS: UN MIJLOC DE,\nMODERNIZARE A PRACTICILOR EDUCATIVE DIN SCOLILE ROMANESTL.\nProfesor Simona Domeana\n\nGrup Seolar .Anghel Saligny\u201d lai\n\n11,\u201d MODALITATI UTILIZATE PENTRU INCURAJAREA MANIFESTARILOR\nELEVILOR IN SITUATH DIVERSE xewonnonnnnnnnanan\n\nProfesor Lidia-Carmen LAMATIC\nScoala Al. 1. Cuza\u201d Podu Hloaei, ls\n12, INSTRUIREA IN SECOLUL XXI- METODA PROIECTELO!\nProfesor Cerasela-lonela GRIGORAS.\n\nGrup Scolar .Anghel Saligny\u201d lagi\n\n13, COMPLEXITATEA IDENTITATH SOCIALE IN CEEA\n(CE PRIVESTE GRUPUL..\n\nProfesor Silvia-Ouna DONDAS,\n\n \n\n \n\n  \n\n \n\n \n\n \n\n \n\n29"
            },
            "10": {
                "class": "text",
                "x": 51,
                "y": 98,
                "height": 26,
                "width": 217,
                "leftCorner": [
                    51,
                    98
                ],
                "rightCorner": [
                    268,
                    124
                ],
                "text": "Sectiunea OM, SOCIETATE, CULTURA"
            },
            "11": {
                "class": "text",
                "x": 246,
                "y": 54,
                "height": 25,
                "width": 107,
                "leftCorner": [
                    246,
                    54
                ],
                "rightCorner": [
                    353,
                    79
                ],
                "text": "= CUPRINS ="
            }
        }
    },
    "img_004": {
        "page": "4",
        "pageWidth": "600",
        "pageHeight": "848",
        "sections": {
            "12": {
                "class": "text",
                "x": 50,
                "y": 622,
                "height": 163,
                "width": 497,
                "leftCorner": [
                    50,
                    622
                ],
                "rightCorner": [
                    547,
                    785
                ],
                "text": "22, INSTALATI ELECTRICE PENTRU MILENIUL Il\nProfesor Ilie APETREL\n\nGrup Scolar ,Anghel Saligny\u201d Iasi\n\n23,\u201d UTILIZAREA ENERGIE SOLARE.\n\nProfesor Mihaela GORGAN\n\nProfesor Raruca CHIRIAC\nGrup Scolar ,Anghel Saligny\u201d lagi\n\n24.\" GRUP MOBIL ECOLOGIC COMPACTARE PE.T-URI\n(NSTALATIE UTILA PROTECTIEI MEDIULUD.\n\nProfesor loan ROBU-STEFAN\n\nScoala de Arte si Meserit Moines, Bactu"
            },
            "13": {
                "class": "text",
                "x": 51,
                "y": 595,
                "height": 24,
                "width": 257,
                "leftCorner": [
                    51,
                    595
                ],
                "rightCorner": [
                    308,
                    619
                ],
                "text": "\u2018Sectiunea TEHNOLOGII ALE SECOLULUI XX1"
            },
            "14": {
                "class": "text",
                "x": 50,
                "y": 178,
                "height": 400,
                "width": 499,
                "leftCorner": [
                    50,
                    178
                ],
                "rightCorner": [
                    549,
                    578
                ],
                "text": "45.\nProfesor Magda COZLAC\n\nGrup Scolar ,Anghel Saligny\u201d Ia\n\n16, PROBLEME DIOFANTICE. PROBLEME ALESE DE ARITMETICA\nSITEORIA NUMERELOR..\n\nProfesor Costici VOINEA-AXINTE\n\nGrup Scolar Industrial ,Elie Radu\u201d Botosani\n\n17. POLIEDRE PLATONIC!\n\nProfesor Claudia OLENIUC\n\nGrup Scolar ,.V. Madgearu\u201d lagi\n\nProfesor Mariana OLENIUC\n\nScoala cu clasele I-VIII Bligesti Pascani\n\nIs. CLASA VIRTUAL,\n\nProfesor Daniela GRADINARU\n\nGrup Scolar Anghel Salizny\u201d la\n19.\u201d LUMINA POLARIZATA SI EFECTELE El ASUPRA OMULUL.\nProfesor Adina TEODORESCU\n\nGrup Scolar ,Anghel Saligny\u201d Iasi\n\n20.\u201d CALEFACTIA.\n\nProfesor Mariana STANA\n\nGrup Scolar ,Anghel Saligny\u201d\n21, COMPORTAMENTUL HAOTIC AL UNEL INTERFETE\nDE TIP JOSEPHSON.\n\nProfesor Adriana-Roxana STANA\n\nGrup Scolar Anghel Saligny\u201d Iasi\n\nProfesor Dr. Maricel AGOP\n\nUniversitatea Politehnicd Gh. Asachi\u201d, Iasi\n\nFacultatea de Constructi de Masini si Management Industrial"
            },
            "15": {
                "class": "text",
                "x": 51,
                "y": 150,
                "height": 25,
                "width": 249,
                "leftCorner": [
                    51,
                    150
                ],
                "rightCorner": [
                    300,
                    175
                ],
                "text": "\u2018Sectiunea DIALOGUL STIINTELOR EXACTE"
            },
            "16": {
                "class": "text",
                "x": 50,
                "y": 53,
                "height": 80,
                "width": 498,
                "leftCorner": [
                    50,
                    53
                ],
                "rightCorner": [
                    548,
                    133
                ],
                "text": "Grup Scolar ,Anghel Salign}\n14, INTERDISCIPLINARITATEA IN ACTIVITATEA DIDACTIC.\nProfesor Domnica BEJAN,\n\nProfesor Florentina POSTIRNAC\nGrup Scolar ,Anghel Saligny\u201d Iasi"
            }
        }
    },
    "img_135": {
        "page": "135",
        "pageWidth": "600",
        "pageHeight": "848",
        "sections": {
            "17": {
                "class": "text",
                "x": 286,
                "y": 794,
                "height": 22,
                "width": 29,
                "leftCorner": [
                    286,
                    794
                ],
                "rightCorner": [
                    315,
                    816
                ],
                "text": "133"
            },
            "18": {
                "class": "text",
                "x": 50,
                "y": 647,
                "height": 104,
                "width": 499,
                "leftCorner": [
                    50,
                    647
                ],
                "rightCorner": [
                    549,
                    751
                ],
                "text": "Populatia si acti\nEvolujia numericd a populatiei demonstreaz\u2019 faptul ci in perioada 1930-1992 are loc 0\nublare a num\u00e9rului populatiei din Campulung Moldovenese datoriti mai multor factori: politics\n\npronatalisti din perioada regimului Ceausescu; exodul rural, alimentat de localitiile rurale din jurul\n\u2018orasului; industrializarea regiunii, care atrage dupa sine un aport de populayie din judefele limitrofe\n(Botosani, Iasi; dezvoltareatursticd a zone"
            },
            "19": {
                "class": "text",
                "x": 50,
                "y": 214,
                "height": 442,
                "width": 499,
                "leftCorner": [
                    50,
                    214
                ],
                "rightCorner": [
                    549,
                    656
                ],
                "text": "\u2018Scopul lucrarii\nEvidentiereaimpactuluiantropic asupra aspectului peisagstic al depresiunii Cimpulung\nMoldoveneseimpus de dezvoltareasocio-economic\u00e9 a zonei\nObiectivele\n(01 ~ Localizarea depresiunii Cimpulung Moldovenese in eadrul Carpailor Oriental\n(02 ~IdentiticarearelieFlui zonei Cimpulung Mokdovenese;\n(03 Stbilrea carateristicilor demografice ale zane\n(04 Stuierea formelor de impact antropic asupra zone:\n(05 Monitorizarea impactului antropic asupra elementelor naturale;\n(06 ~ Idemificarea souflor de reabiltae natural\n(07 \u2014 Diseminarea informe a nivel de comunitte local privind Convengia peisajul\nAyezare geografici\n\nDepresiunea Cimpulung Moldovenese este situati in sudul Obeine! Feredew pe Valea\nMoldovei inte Pojorita si Vama si este orientati NV ~ SE, find incadrata inte dous sectoare mai\ninguste: heile Pojoritet in amonte gi Srimtura Rosie in aval. Ine acest limite depresiunea se\n<dezvolt\u00e9 pe Valea Moldovei care se lirgeste mult aici ciptind un aspeet de ,c\u00e9mpulung\u201d, datorits\nfaciesului petrograic mai sor de erodatreprezentat mai ales desisturi negre eretaice din patea de\nvests central eapatului sudic al Obcinei Feredeu, Limita depresiuni este mult mai carl pe rama\nsued unde MuneeiiRarduluicoboars trangant cu denveliri de 400 ~ $00 m form\u00e9nd un aliniament\n<de-migurialcituit de la vest la est din: Magura (1176 m), Runcul (1129 m), Bodea(1073 m) gi\nCucoara (944 m),\n\nLa nivel abe\u2019 riului Moldova se inser altitudinile cele mai coborite de 675 m in Chile\nPjoriti ict 100 m mai putin la ese din depresiune.\n\nRaportind aceasta diferent de altitude la distanya dintre cele dou puncte extreme ale\ndepresiuni care este de aproximatv 15 km, se poate consalafaptl ef fundul depresiuni se neling\nin sensulcurgetiapelor cu aproximativ Tavkm. in mod obiguit se consider ci aliudinea medie a"
            },
            "20": {
                "class": "text",
                "x": 270,
                "y": 133,
                "height": 58,
                "width": 280,
                "leftCorner": [
                    270,
                    133
                ],
                "rightCorner": [
                    550,
                    191
                ],
                "text": "Bouhar Simona si Rotar Nicoleta, clasa a Xl-a E\nColegiut Sitvic ,Bucovina\u201d Campulung Moldovenese\n\n \n\nProfesori indrumatori Ana Latis si Ramona Popescu"
            },
            "21": {
                "class": "text",
                "x": 138,
                "y": 53,
                "height": 49,
                "width": 324,
                "leftCorner": [
                    138,
                    53
                ],
                "rightCorner": [
                    462,
                    102
                ],
                "text": "IMPACTUL ANTROPIC ASUPRA DEPRI\n\n \n\nUNG MOLDOV!"
            }
        }
    },
    "img_136": {
        "page": "136",
        "pageWidth": "600",
        "pageHeight": "848",
        "sections": {
            "22": {
                "class": "text",
                "x": 286,
                "y": 794,
                "height": 22,
                "width": 29,
                "leftCorner": [
                    286,
                    794
                ],
                "rightCorner": [
                    315,
                    816
                ],
                "text": "134"
            },
            "23": {
                "class": "text",
                "x": 50,
                "y": 53,
                "height": 728,
                "width": 500,
                "leftCorner": [
                    50,
                    53
                ],
                "rightCorner": [
                    550,
                    781
                ],
                "text": "\u2018Studiul asupra structurii populatici arati 0 scidere numeric\u2019 a populatiei active gi aparitia\nfenomenului de imbitrinire a populaiei, care are la baz scdderea natalitti si migrafia fortei de\nrmuncd datorat\u00e9 deelinului economic al zonei\nLa un necesar de locuri de muned de 240/1000 locuitori, necesarul actual al acestora este de\n7 820, cu un deficit mare acoperit partial de migratia populajei active spre rile din vestul Europei\nDeclinul economic al zonei a atras dupa sine si un declin al aspectului oragului\n= Centrata termicd a orasului nu functioneazai;\n= Clidirite de blocuri nu au fost reabilitate iar numarul de apartamente nelocuite a crescut;,\n= Spatile veri se amenajeaza cu dificultate si in timp indelungat;\n= Se construiese claditi noi lipsite de personalitatetraditionald locala si amplasate in locuri cu\nrise mare de inundafi,aluneciri de teren sau foarte aproape de rezervatii;\n= Infrastructura stradald este deteriorat;\n\n \n\n= Nus-au amenajat spajii pentru timpul liber pentru tineri sau varstnici,\nEconomia actual\u00e9 a municipiului a suferit transforma si se bazeaza pe urmatoarele tipuri de\nactivitai:\n= Activitati de tip industrial gi de construct:\n+ Activitati agricole gi silvice:\n= Activitat turistices\n+ Transporturi si depozitare;\n+ Activitati din domeniul servicilor.\nImpactul antropic in Depresiunea Campulung Moldovenese\n1. Perimetrul construit al orasului\n\u2018Vatra orasului igi are originea pe pariul Valea Caselor, la intrare in depresiunea Campulung\nMoldovenese dinspre Suceava, ulterior datorit\u00e9 dezvoltirii urbane si spatului limitat al vai\npltdului, agezarea sa extins spre vest prin defrisarea versantilor Obcinei Feredeu si a teraselor\nMoldovei de pe versantul Rardului\n[Impactul antropic determinat de extinderea perimetrului construit const in:\n+ Defiisiile datorate eresteri necesarului de spatiu pentru constructis\n+ Scdderea spatiului verde/cap locuitor in zona central;\n+ Aparitia de cladiri noi, cw\norasuluis\n+ Aglomerarea in zona centrala prin eresterea numarului de constructii, masini si ipsa\nspatilor de parcare ceea ce duce la degradarea calitiitaerului sia peisajuli\n2. Managementul deseurilor\nImpactul antropic determinat de managementul actual al deseurilor publice din Cimpulung\nMoldovenese consti\n+ Poluarea aerului, deoarece deseurile aruncate la intimplare se degradeaza intr-un\ntimp indelungat;\n+ Poluarea apelor, datorita deycurior care se arunca pe malul acestora;\n= Modificarea ecosistemelor acvatice prin acumularea degeurilor pe malurile Moldovei\nsiale afluentilor;\n~ Degradarea aspectului oragului datoriti gestionari inadecvate a deseurilor si gradului\nde civilizatie a populate;\n= Impactul gropii de gunoi asupra tuturor elementelor de mediu: solurile sunt afectate\nprin infilrarea levigatului, apa freatic\u2019 este infestatl, polurea acrului datoriti\n\n \n\nlfm mari care nu se integreaza aspectului specific al"
            }
        }
    },
    "img_137": {
        "page": "137",
        "pageWidth": "600",
        "pageHeight": "848",
        "sections": {
            "24": {
                "class": "text",
                "x": 50,
                "y": 53,
                "height": 763,
                "width": 499,
                "leftCorner": [
                    50,
                    53
                ],
                "rightCorner": [
                    549,
                    816
                ],
                "text": "mirosurilor, vegetatia din jurul gropii de gunoi este modificata, suprafata de teren pe\ncare sunt amplasate gunoaiele se extinde gi iese din cireuitul agricol\n\n4. Talerile legale silegale de padure\n\nImpactul wigrlor de pdure asupra elementelor de mediu\n\n- Freevenja si intensitatea viturilor a erescut mai ales in timpul veri datoriti\nprecipitatiilor torentiale; dupa anul 2000 aproape in fiecare an au avut loc iesiri di\n\u2018mated ale paraiclor mici, afluente ale Moldovei (Valea Seaci, Izvorul Alb,\nCorlajeni)\n\n= Pe malul apelor numdrul grimezilor de rumegus a erescut, datoritt numarului mare\nde instalajii de debitare a lemnului situate pe cursul afluenjlor Moldovei; in timpul\nviiturilor apele capati turbiditate ridicati, afectind biomurile acvatice de api\ncurgitoare;\n\n- Prin deftigirile necontrolate din perimetrul zonelor construite datortd tasirilor gi\ningreunaii terenurilor apar condiit favorabile pentru declansatea alunecirilor de\nteren; exist alunecdri active pe Paraurile Sandru, Corkieni si Deia;\n\n- Prin tierile de padure se degradeaza terenurile care treptat ies din circuitulsilvie,\nfind transformate in terenuri de pasunat cea ce duce la aparitia formelor de tip\nspied de vache\u201d;\n\n+ Scdderea suprafejelor forestiere si impactul lucririlor de explostare a padurii\nafecteaza biodiversitatea prin sciderea habitatelordiferitelor specii si modificdri de\n\u2018comportament date de restringerea de spat;\n\n+ Are loc degradarea peisajului ceea ce poate duce la sedderea potentalului triste al\n\n4. Turismul necontrolat\n\n{mpactul turismului necontrolat asupra elementolor de mediu\n\n= Poluarea apelor si terenurilor cu resturi ale diferitelor forme de turism: Pet-uri, doze\n\u2018metalic, ambalaje de carton, hirtie, plastic, sticle, deyeuripericuloase (bateri, piese\nuzate, uleiuri uzate, detergenti, combustbili, seutece si tampoane folosite)\n\n+ Influenfarea habitatului natural al diferitelor specii, prin zzomot, deseuti, incendii\nete\n\n \n\n \n\n+ Poluarea esteticd a peisajelor, nu numai prin introducerea degcuritor intr-un mediu\nnatural, ci i prin comportamentul necivilizat al turistului, care rupe plante rare si\n\u2018ocrotite si agreseazi dferite spect de animale\n~ Braconarea unor exemplare valoroase si a unor specii rare si ocrotite, cum ar fi\ncocosul de munte, cocogul de mesteaciin, linxul, sitari, cervidele si uryii pentru\ntrofee.\n5. Poluarea peisajului arhirectural\nImpactul poluiri peisajului arhitectural\n+ Poluarea estetici a peisajului urban prin picrderea specificului arhitectural si\ntraditional,\n+ Sciderea atractivititii turistice prin diminuarea valorii_ specifice arhitectuii\ntraditionale bucovinene.\n\n \n\n= Aparitia pericolului de stergere a personalititii oragului Campulung_printro\nurbanizare fortat\n\n= Educarea noi generatii in spiritul adoptiiistlului modern, impersonal in defavoarea\nvechilor tradi i obiceiuri de utilizare a resurselor locale\n\n \n\n13s"
            }
        }
    },
    "img_138": {
        "page": "138",
        "pageWidth": "600",
        "pageHeight": "848",
        "sections": {
            "25": {
                "class": "text",
                "x": 286,
                "y": 794,
                "height": 22,
                "width": 30,
                "leftCorner": [
                    286,
                    794
                ],
                "rightCorner": [
                    316,
                    816
                ],
                "text": "136,"
            },
            "26": {
                "class": "text",
                "x": 50,
                "y": 617,
                "height": 105,
                "width": 500,
                "leftCorner": [
                    50,
                    617
                ],
                "rightCorner": [
                    550,
                    722
                ],
                "text": "1. Gratian Jucan, 1995 C\u00e9impulung Moldovenese Istoric ~ Cultural ~ Turistic\n2. Primaria municipiului Campulung Moldovenese, 2009 - Caimpulung Moldovenese Repere\n\nturistice\n3, Dumitru Rusan, Marcel Zahaniciue, 1996 - Zona emografica C\u00e9impulung Moldovenese\n\n4, Mihaitescu V. (1976) Orasul ca element de peisaj si ca factor climatogen, Simpoziontl de\nclimatologie urbana si combaterea poluiti aerului, lay"
            },
            "27": {
                "class": "text",
                "x": 51,
                "y": 586,
                "height": 24,
                "width": 76,
                "leftCorner": [
                    51,
                    586
                ],
                "rightCorner": [
                    127,
                    610
                ],
                "text": "Bibliogratie:"
            },
            "28": {
                "class": "text",
                "x": 50,
                "y": 53,
                "height": 509,
                "width": 500,
                "leftCorner": [
                    50,
                    53
                ],
                "rightCorner": [
                    550,
                    562
                ],
                "text": "Identificarea solutilor de reabilitare naturald a zonei\n\n\u2018+ Extinderea spayilui verde de fa 14 meap loc, ct este in prezent la 20mcap loc,\n\nconform normeloreuropene, prin reabilitarea spatilor din lungul vaii Moldovei sia\n\ncolor din jurul blocurilo,infinjarea de noi parcuri si moderizarea si intrtinerea\nparcrilorexstente;\n\n+ Implementarea legislate\u2019 spectice Conventei Pesajului la nivel national si local\npentru pstrareaspecifiului zon, evitindu-se ast ptrunderea ktschulu\n\n+ Promovarea unei campanii de impidurre a zonelor afecate de ttieri si de\ndoboraturile de vn, prin implicarea populate locale in activiti de volunarat;\n\n+ Introducer sistemluiintgrat la nivel judetean de gestionare a deycurilo, prin\ndeschiderea sae\u2019 de transfer locale si @depozitlu de la Mestecnis, momentan in\nfaz de proicct aprobat;\n\n+ Educareatnerilor prin intoducerea de CDL-ur la nivel eolilor, prin activi\nextrajcolare, de voluntariat pent dervoltarea nor apitdiniprivind alegerea nei\ncariere profesionale, care si le permit\u00e9 ocuparea nor locuri de munet in zon\nasigurind dezvoliare local i evitaea migrates\n\n+ Dezvolarea patiotismului foal privnd conservarea patrimoniuli natural, cultural,\nistorc si arhitectural al zonei prin implicarea tinerilor in proieete de dezvotare\nlocal.\n\nDiseminare informatie la nivel de comunitate localdprivind Convent peisjul\n\nProblematica.pesajului este absenti in legisla rom\u00e9neasci, de accea se impune\nimoducerea in actele normative a unor dispoztt minimale derivate din ratificarea Conveniel\nEuropene a Peisajlor la care Romina a fst semnatar, in acest sens, un rol important reve\n\u2018ONGurilor ca reprezentanti ai societi civle pentr a initia proecte dele, cae fie dezbarute\ncu atoritjile locales aos fe inaintatefrurlor superiore pentru aprobare\n\nDiseminare informatie prvind aplicarea la nivel local a Convene pesaulu se pote face\n\nin sein publceiiiate de autor locale eu invitarea reprezentaniorpatonatuli si\n\na societiticvile:\n\n= prin intermedi mass-medici (TV SAT Suceava, radio local, Monitorul de Suceava)\n\n= prin prezentrea proectlui in cadrul unor manifestri locale iunie-Ziua Mediu, 22\nprilie-Ziva Pimanului, 22 marte-Ziua Ape)"
            }
        }
    },
    "img_139": {
        "page": "139",
        "pageWidth": "600",
        "pageHeight": "848",
        "sections": {}
    },
    "img_140": {
        "page": "140",
        "pageWidth": "600",
        "pageHeight": "848",
        "sections": {
            "29": {
                "class": "text",
                "x": 161,
                "y": 680,
                "height": 94,
                "width": 274,
                "leftCorner": [
                    161,
                    680
                ],
                "rightCorner": [
                    435,
                    774
                ],
                "text": "EDITURA $I TIPOGRAFIA PIM\nSoseaua Stefan eel Mate gi Sfint ne. 4, lagi ~ 700497\n\u201cTel:0730.086.676; Fax: 0332.440.730\n\nE-mail: editura.pim@ gmail.com\nwww:pimeopy.r0"
            },
            "30": {}
        }
    }
}